{"trial_id": "005", "hyperparameters": {"space": [{"class_name": "Int", "config": {"name": "1", "default": null, "conditions": [], "min_value": 2, "max_value": 11, "step": 1, "sampling": "linear"}}], "values": {"1": 10}}, "metrics": {"metrics": {"loss": {"direction": "min", "observations": [{"value": [0.28197599947452545], "step": 91}]}, "binary_accuracy": {"direction": "max", "observations": [{"value": [0.8784988224506378], "step": 91}]}, "val_loss": {"direction": "min", "observations": [{"value": [0.2820303589105606], "step": 91}]}, "val_binary_accuracy": {"direction": "max", "observations": [{"value": [0.87886643409729], "step": 91}]}}}, "score": 0.87886643409729, "best_step": 91, "status": "COMPLETED", "message": null}