{"trial_id": "008", "hyperparameters": {"space": [{"class_name": "Int", "config": {"name": "1", "default": null, "conditions": [], "min_value": 2, "max_value": 11, "step": 1, "sampling": "linear"}}], "values": {"1": 2}}, "metrics": {"metrics": {"loss": {"direction": "min", "observations": [{"value": [0.38770322501659393], "step": 56}]}, "binary_accuracy": {"direction": "max", "observations": [{"value": [0.8492372632026672], "step": 56}]}, "val_loss": {"direction": "min", "observations": [{"value": [0.3876636177301407], "step": 56}]}, "val_binary_accuracy": {"direction": "max", "observations": [{"value": [0.8502257168292999], "step": 56}]}}}, "score": 0.8502257168292999, "best_step": 56, "status": "COMPLETED", "message": null}