{"trial_id": "35", "hyperparameters": {"space": [{"class_name": "Int", "config": {"name": "1", "default": null, "conditions": [], "min_value": 2, "max_value": 11, "step": 1, "sampling": "linear"}}, {"class_name": "Float", "config": {"name": "learning_rate", "default": 0.0001, "conditions": [], "min_value": 0.0001, "max_value": 0.01, "step": null, "sampling": "log"}}], "values": {"1": 10, "learning_rate": 0.0023057788252851554}}, "metrics": {"metrics": {"loss": {"direction": "min", "observations": [{"value": [0.26874715089797974], "step": 27}]}, "binary_accuracy": {"direction": "max", "observations": [{"value": [0.912959635257721], "step": 27}]}, "val_loss": {"direction": "min", "observations": [{"value": [0.26695141196250916], "step": 27}]}, "val_binary_accuracy": {"direction": "max", "observations": [{"value": [0.9135093688964844], "step": 27}]}}}, "score": 0.9135093688964844, "best_step": 27, "status": "COMPLETED", "message": null}