{"trial_id": "032", "hyperparameters": {"space": [{"class_name": "Int", "config": {"name": "1", "default": null, "conditions": [], "min_value": 1, "max_value": 30, "step": 1, "sampling": "linear"}}, {"class_name": "Int", "config": {"name": "2", "default": null, "conditions": [], "min_value": 1, "max_value": 30, "step": 1, "sampling": "linear"}}, {"class_name": "Int", "config": {"name": "3", "default": null, "conditions": [], "min_value": 1, "max_value": 30, "step": 1, "sampling": "linear"}}, {"class_name": "Int", "config": {"name": "4", "default": null, "conditions": [], "min_value": 1, "max_value": 30, "step": 1, "sampling": "linear"}}, {"class_name": "Int", "config": {"name": "5", "default": null, "conditions": [], "min_value": 1, "max_value": 30, "step": 1, "sampling": "linear"}}], "values": {"1": 13, "2": 26, "3": 29, "4": 25, "5": 18}}, "metrics": {"metrics": {"loss": {"direction": "min", "observations": [{"value": [0.2798200398683548], "step": 67}]}, "binary_accuracy": {"direction": "max", "observations": [{"value": [0.8793869614601135], "step": 67}]}, "val_loss": {"direction": "min", "observations": [{"value": [0.27960535883903503], "step": 67}]}, "val_binary_accuracy": {"direction": "max", "observations": [{"value": [0.8798229992389679], "step": 67}]}}}, "score": 0.8798229992389679, "best_step": 67, "status": "COMPLETED", "message": null}