{"trial_id": "049", "hyperparameters": {"space": [{"class_name": "Int", "config": {"name": "1", "default": null, "conditions": [], "min_value": 2, "max_value": 11, "step": 1, "sampling": "linear"}}, {"class_name": "Float", "config": {"name": "learning_rate", "default": 0.0001, "conditions": [], "min_value": 0.0001, "max_value": 0.01, "step": null, "sampling": "log"}}], "values": {"1": 6, "learning_rate": 0.006531232722772538}}, "metrics": {"metrics": {"loss": {"direction": "min", "observations": [{"value": [0.39348603785037994], "step": 24}]}, "binary_accuracy": {"direction": "max", "observations": [{"value": [0.8498348593711853], "step": 24}]}, "val_loss": {"direction": "min", "observations": [{"value": [0.39304618537425995], "step": 24}]}, "val_binary_accuracy": {"direction": "max", "observations": [{"value": [0.850925624370575], "step": 24}]}}}, "score": 0.850925624370575, "best_step": 24, "status": "COMPLETED", "message": null}